deeplint/__init__.py
deeplint/__main__.py
deeplint/cli.py
deeplint/config.py
deeplint/detector.py
deeplint/language_detector.py
deeplint/reporter.py
deeplint/scoring.py
deeplint/analyzers/__init__.py
deeplint/analyzers/ast_analyzer.py
deeplint/analyzers/import_validator.py
deeplint/patterns/__init__.py
deeplint/patterns/base.py
deeplint/patterns/hallucinations.py
deeplint/patterns/helpers.py
deeplint/patterns/noise.py
deeplint/patterns/structure.py
deeplint/patterns/style.py
deeplint/patterns/go/__init__.py
deeplint/patterns/go/noise.py
deeplint/patterns/go/style.py
deeplint/patterns/js/__init__.py
deeplint/patterns/js/hallucinations.py
deeplint/patterns/js/noise.py
deeplint/patterns/js/react.py
deeplint/patterns/js/structure.py
deeplint/patterns/js/style.py
deeplint/patterns/js/typescript.py
deeplint-0.0.2.dist-info/METADATA
deeplint-0.0.2.dist-info/WHEEL
deeplint-0.0.2.dist-info/entry_points.txt
deeplint-0.0.2.dist-info/RECORD
