Metadata-Version: 2.4
Name: deeplint
Version: 0.0.2
Summary: Multi-language AI Slop Detector - Intelligent detection of AI-generated code anti-patterns
Project-URL: Homepage, https://github.com/del-zhenwu/deeplint
Project-URL: Repository, https://github.com/del-zhenwu/deeplint
Author: Rob Fox
License-Expression: MIT
Keywords: ai,code-quality,deep-learning,linter,static-analysis
Classifier: Development Status :: 3 - Alpha
Classifier: Environment :: Console
Classifier: Intended Audience :: Developers
Classifier: License :: OSI Approved :: MIT License
Classifier: Programming Language :: Python :: 3
Classifier: Programming Language :: Python :: 3.9
Classifier: Programming Language :: Python :: 3.10
Classifier: Programming Language :: Python :: 3.11
Classifier: Programming Language :: Python :: 3.12
Classifier: Topic :: Software Development :: Quality Assurance
Requires-Python: >=3.9
Provides-Extra: all
Requires-Dist: rich>=13.0; extra == 'all'
Requires-Dist: tomli>=2.0; (python_version < '3.11') and extra == 'all'
Provides-Extra: dev
Requires-Dist: black>=23.0; extra == 'dev'
Requires-Dist: isort>=5.0; extra == 'dev'
Requires-Dist: mypy>=1.0; extra == 'dev'
Requires-Dist: pip-audit>=2.0; extra == 'dev'
Requires-Dist: pre-commit>=3.0; extra == 'dev'
Requires-Dist: pytest-cov>=4.0; extra == 'dev'
Requires-Dist: pytest>=7.0; extra == 'dev'
Requires-Dist: ruff>=0.8.0; extra == 'dev'
Provides-Extra: rich
Requires-Dist: rich>=13.0; extra == 'rich'
Provides-Extra: toml
Requires-Dist: tomli>=2.0; (python_version < '3.11') and extra == 'toml'
